HISTORY.md
LICENSE
MANIFEST.in
README.md
requirements.txt
setup.py
bin/exo
bin/exoline
exoline/__init__.py
exoline/exo.py
exoline/exocommon.py
exoline/serieswriter.py
exoline.egg-info/PKG-INFO
exoline.egg-info/SOURCES.txt
exoline.egg-info/dependency_links.txt
exoline.egg-info/not-zip-safe
exoline.egg-info/pbr.json
exoline.egg-info/requires.txt
exoline.egg-info/top_level.txt
exoline/plugins/__init__.py
exoline/plugins/_example.py
exoline/plugins/aliases.py
exoline/plugins/dump.py
exoline/plugins/keys.py
exoline/plugins/makeShortcuts.py
exoline/plugins/meta.py
exoline/plugins/move.py
exoline/plugins/ndup.py
exoline/plugins/provision.py
exoline/plugins/search.py
exoline/plugins/spec.py
exoline/plugins/switches.py
exoline/plugins/transform.py
test/test.py
test/testconfig.py