Metadata-Version: 1.0
Name: exoline
Version: 0.9.21
Summary: Command line interface for Exosite platform.
Home-page: http://github.com/exosite/exoline
Author: Dan Weaver
Author-email: danweaver@exosite.com
License: UNKNOWN
Keywords: exosite,onep,one platform,m2m,iot,cli
Platform: UNKNOWN
